pawpd/__init__.py
pawpd/channel.py
pawpd/color.py
pawpd/embed.py
pawpd/guild.py
pawpd/http.py
pawpd/intents.py
pawpd/message.py
pawpd/msg.py
pawpd/user.py
pawpd-1.0.1.dist-info/licenses/LICENSE
pawpd-1.0.1.dist-info/METADATA
pawpd-1.0.1.dist-info/WHEEL
pawpd-1.0.1.dist-info/top_level.txt
pawpd-1.0.1.dist-info/RECORD
