Metadata-Version: 2.4
Name: PaWpD
Version: 1.0.1
Summary: PaWpD is a package for creating discord bots. PaWpD is a minimal client made for performance and low latencies.
Author-email: Lordpomind <support@mutipe.com>
License-Expression: MIT
Classifier: Programming Language :: Python :: 3
Classifier: Operating System :: OS Independent
Requires-Python: >=3.9
License-File: LICENSE
Requires-Dist: aiohttp
Requires-Dist: websockets
Dynamic: license-file
